setup.py
simple_calc/__init__.py
simple_calc/simple_calc.py
simple_calc_kw.egg-info/PKG-INFO
simple_calc_kw.egg-info/SOURCES.txt
simple_calc_kw.egg-info/dependency_links.txt
simple_calc_kw.egg-info/not-zip-safe
simple_calc_kw.egg-info/top_level.txt