Metadata-Version: 1.0
Name: simple-calc-kw
Version: 1.0
Summary: To calculate the addition, subtraction, multiplication and division of two numbers. This exercise serves as a practice                       PyPi publishing
Home-page: UNKNOWN
Author: Tan Ke Wei
Author-email: keweiUTP@gmail.com
License: UNKNOWN
Platform: UNKNOWN
